manuf/__init__.py
manuf/__main__.py
manuf/manuf
manuf/manuf.py
manuf-1.1.5.dist-info/LICENSE.txt
manuf-1.1.5.dist-info/METADATA
manuf-1.1.5.dist-info/WHEEL
manuf-1.1.5.dist-info/entry_points.txt
manuf-1.1.5.dist-info/top_level.txt
manuf-1.1.5.dist-info/RECORD
