Metadata-Version: 2.1
Name: manuf
Version: 1.1.5
Summary: Parser library for Wireshark's OUI database
Home-page: https://github.com/coolbho3k/manuf/
Author: Michael Huang
License: Apache License 2.0 or GPLv3
Keywords: manuf,mac address,networking
Platform: UNKNOWN
